pytest_allure_step/__init__.py
pytest_allure_step/allure_logger.py
pytest_allure_step-0.1.0.dist-info/licenses/LICENSE
pytest_allure_step-0.1.0.dist-info/METADATA
pytest_allure_step-0.1.0.dist-info/WHEEL
pytest_allure_step-0.1.0.dist-info/top_level.txt
pytest_allure_step-0.1.0.dist-info/RECORD
