Metadata-Version: 2.4
Name: pytest-allure-step
Version: 0.1.0
Summary: Enhanced logging integration with Allure reports for pytest
Author-email: Deekshith Poojary <deekshithpoojary355@gmail.com>
Maintainer-email: Deekshith Poojary <deekshithpoojary355@gmail.com>
License: MIT
Project-URL: Homepage, https://github.com/deekshith-poojary98/pytest-allure-step
Project-URL: Repository, https://github.com/deekshith-poojary98/pytest-allure-step
Project-URL: Documentation, https://github.com/deekshith-poojary98/pytest-allure-step#readme
Project-URL: Bug Tracker, https://github.com/deekshith-poojary98/pytest-allure-step/issues
Project-URL: Changelog, https://github.com/deekshith-poojary98/pytest-allure-step/blob/main/CHANGELOG.md
Project-URL: Source, https://github.com/deekshith-poojary98/pytest-allure-step
Keywords: pytest,allure,logging,testing
Classifier: Development Status :: 3 - Alpha
Classifier: Intended Audience :: Developers
Classifier: License :: OSI Approved :: MIT License
Classifier: Operating System :: OS Independent
Classifier: Programming Language :: Python :: 3
Classifier: Programming Language :: Python :: 3.7
Classifier: Programming Language :: Python :: 3.8
Classifier: Programming Language :: Python :: 3.9
Classifier: Programming Language :: Python :: 3.10
Classifier: Programming Language :: Python :: 3.11
Classifier: Topic :: Software Development :: Testing
Classifier: Topic :: Software Development :: Libraries :: Python Modules
Classifier: Framework :: Pytest
Requires-Python: >=3.7
License-File: LICENSE
Requires-Dist: allure-pytest>=2.9.0
Requires-Dist: pytest>=6.0.0
Provides-Extra: dev
Requires-Dist: pytest>=6.0.0; extra == "dev"
Requires-Dist: allure-pytest>=2.9.0; extra == "dev"
Requires-Dist: black>=22.0.0; extra == "dev"
Requires-Dist: flake8>=4.0.0; extra == "dev"
Requires-Dist: mypy>=0.950; extra == "dev"
Dynamic: license-file
